petsafe_smartfeed/__init__.py
petsafe_smartfeed/__main__.py
petsafe_smartfeed/api.py
petsafe_smartfeed/devices.py
petsafe_smartfeed-1.3.dist-info/LICENSE
petsafe_smartfeed-1.3.dist-info/METADATA
petsafe_smartfeed-1.3.dist-info/WHEEL
petsafe_smartfeed-1.3.dist-info/top_level.txt
petsafe_smartfeed-1.3.dist-info/RECORD
