Metadata-Version: 2.1
Name: petsafe-smartfeed
Version: 1.3
Summary: Provides ability to connect and control a PetSafe Smart Feed device using the PetSafe-SmartFeed API.
Home-page: https://github.com/techzune/petsafe_smartfeed
Author: Jordan Stremming
Author-email: jcstremming@gmail.com
License: MIT
Platform: UNKNOWN
Classifier: Programming Language :: Python :: 3
Classifier: License :: OSI Approved :: MIT License
Classifier: Operating System :: OS Independent
Requires-Python: >=3.6
License-File: LICENSE
Requires-Dist: requests
